[{"code":230602,"districtCode":2306,"name":"เกาะกูด","zip":23000},{"code":230701,"districtCode":2307,"name":"เกาะช้าง","zip":23170},{"code":230702,"districtCode":2307,"name":"เกาะช้างใต้","zip":23170},{"code":230601,"districtCode":2306,"name":"เกาะหมาก","zip":23000},{"code":230301,"districtCode":2303,"name":"เขาสมิง","zip":23130},{"code":230201,"districtCode":2302,"name":"คลองใหญ่","zip":23110},{"code":230507,"districtCode":2305,"name":"คลองใหญ่","zip":23120},{"code":230402,"districtCode":2304,"name":"ช้างทูน","zip":23140},{"code":230113,"districtCode":2301,"name":"ชำราก","zip":23000},{"code":230403,"districtCode":2304,"name":"ด่านชุมพล","zip":23140},{"code":230112,"districtCode":2301,"name":"ตะกาง","zip":23000},{"code":230111,"districtCode":2301,"name":"ท่ากุ่ม","zip":23000},{"code":230110,"districtCode":2301,"name":"ท่าพริก","zip":23000},{"code":230304,"districtCode":2303,"name":"ท่าโสม","zip":23150},{"code":230308,"districtCode":2303,"name":"ทุ่งนนทรี","zip":23130},{"code":230307,"districtCode":2303,"name":"เทพนิมิต","zip":23150},{"code":230405,"districtCode":2304,"name":"นนทรีย์","zip":23140},{"code":230502,"districtCode":2305,"name":"น้ำเชี่ยว","zip":23120},{"code":230109,"districtCode":2301,"name":"เนินทราย","zip":23000},{"code":230401,"districtCode":2304,"name":"บ่อพลอย","zip":23140},{"code":230503,"districtCode":2305,"name":"บางปิด","zip":23120},{"code":230101,"districtCode":2301,"name":"บางพระ","zip":23000},{"code":230306,"districtCode":2303,"name":"ประณีต","zip":23150},{"code":230202,"districtCode":2302,"name":"ไม้รูด","zip":23110},{"code":230107,"districtCode":2301,"name":"วังกระแจะ","zip":23000},{"code":230303,"districtCode":2303,"name":"วังตะเคียน","zip":23130},{"code":230305,"districtCode":2303,"name":"สะตอ","zip":23150},{"code":230302,"districtCode":2303,"name":"แสนตุ้ง","zip":23150},{"code":230104,"districtCode":2301,"name":"หนองคันทรง","zip":23000},{"code":230404,"districtCode":2304,"name":"หนองบอน","zip":23140},{"code":230102,"districtCode":2301,"name":"หนองเสม็ด","zip":23000},{"code":230103,"districtCode":2301,"name":"หนองโสน","zip":23000},{"code":230105,"districtCode":2301,"name":"ห้วงน้ำขาว","zip":23000},{"code":230108,"districtCode":2301,"name":"ห้วยแร้ง","zip":23000},{"code":230203,"districtCode":2302,"name":"หาดเล็ก","zip":23110},{"code":230114,"districtCode":2301,"name":"แหลมกลัด","zip":23000},{"code":230501,"districtCode":2305,"name":"แหลมงอบ","zip":23120},{"code":230106,"districtCode":2301,"name":"อ่าวใหญ่","zip":23000}]