[{"code":430104,"districtCode":4301,"name":"กวนวัน","zip":43000},{"code":430203,"districtCode":4302,"name":"กองนาง","zip":43110},{"code":430503,"districtCode":4305,"name":"กุดบง","zip":43120},{"code":430801,"districtCode":4308,"name":"แก้งไก่","zip":43160},{"code":431402,"districtCode":4314,"name":"คอกช้าง","zip":43100},{"code":430110,"districtCode":4301,"name":"ค่ายบกหวาน","zip":43100},{"code":430204,"districtCode":4302,"name":"โคกคอน","zip":43110},{"code":430501,"districtCode":4305,"name":"จุมพล","zip":43120},{"code":430504,"districtCode":4305,"name":"ชุมช้าง","zip":43120},{"code":430509,"districtCode":4305,"name":"เซิม","zip":43120},{"code":431703,"districtCode":4317,"name":"ด่านศรีสุข","zip":43130},{"code":430201,"districtCode":4302,"name":"ท่าบ่อ","zip":43110},{"code":430506,"districtCode":4305,"name":"ทุ่งหลวง","zip":43120},{"code":430208,"districtCode":4302,"name":"นาข่า","zip":43110},{"code":430804,"districtCode":4308,"name":"นางิ้ว","zip":43160},{"code":431502,"districtCode":4315,"name":"นาดี","zip":43120},{"code":431602,"districtCode":4316,"name":"นาทับไฮ","zip":43120},{"code":430508,"districtCode":4305,"name":"นาหนัง","zip":43120},{"code":430202,"districtCode":4302,"name":"น้ำโมง","zip":43110},{"code":430101,"districtCode":4301,"name":"ในเมือง","zip":43000},{"code":430109,"districtCode":4301,"name":"บ้านเดื่อ","zip":43000},{"code":430205,"districtCode":4302,"name":"บ้านเดื่อ","zip":43110},{"code":431603,"districtCode":4316,"name":"บ้านต้อน","zip":43120},{"code":430206,"districtCode":4302,"name":"บ้านถ่อน","zip":43110},{"code":430521,"districtCode":4305,"name":"บ้านผือ","zip":43120},{"code":431403,"districtCode":4314,"name":"บ้านฝาง","zip":43100},{"code":430513,"districtCode":4305,"name":"บ้านโพธิ์","zip":43120},{"code":430803,"districtCode":4308,"name":"บ้านม่วง","zip":43160},{"code":430207,"districtCode":4302,"name":"บ้านว่าน","zip":43110},{"code":430703,"districtCode":4307,"name":"บ้านหม้อ","zip":43130},{"code":430117,"districtCode":4301,"name":"ปะโค","zip":43000},{"code":430802,"districtCode":4308,"name":"ผาตั้ง","zip":43160},{"code":431501,"districtCode":4315,"name":"เฝ้าไร่","zip":43120},{"code":430113,"districtCode":4301,"name":"พระธาตุบังพวน","zip":43100},{"code":431604,"districtCode":4316,"name":"พระบาทนาสิงห์","zip":43120},{"code":430704,"districtCode":4307,"name":"พระพุทธบาท","zip":43130},{"code":430701,"districtCode":4307,"name":"พานพร้าว","zip":43130},{"code":430103,"districtCode":4301,"name":"โพธิ์ชัย","zip":43000},{"code":431701,"districtCode":4317,"name":"โพธิ์ตาก","zip":43130},{"code":431702,"districtCode":4317,"name":"โพนทอง","zip":43130},{"code":431605,"districtCode":4316,"name":"โพนแพง","zip":43120},{"code":430111,"districtCode":4301,"name":"โพนสว่าง","zip":43100},{"code":430209,"districtCode":4302,"name":"โพนสา","zip":43110},{"code":430102,"districtCode":4301,"name":"มีชัย","zip":43000},{"code":430118,"districtCode":4301,"name":"เมืองหมี","zip":43000},{"code":431601,"districtCode":4316,"name":"รัตนวาปี","zip":43120},{"code":431504,"districtCode":4315,"name":"วังหลวง","zip":43120},{"code":430106,"districtCode":4301,"name":"วัดธาตุ","zip":43000},{"code":430502,"districtCode":4305,"name":"วัดหลวง","zip":43120},{"code":430105,"districtCode":4301,"name":"เวียงคุก","zip":43000},{"code":431401,"districtCode":4314,"name":"สระใคร","zip":43100},{"code":430522,"districtCode":4305,"name":"สร้างนางขาว","zip":43120},{"code":430805,"districtCode":4308,"name":"สังคม","zip":43160},{"code":430119,"districtCode":4301,"name":"สีกาย","zip":43000},{"code":430116,"districtCode":4301,"name":"หนองกอมเกาะ","zip":43000},{"code":430210,"districtCode":4302,"name":"หนองนาง","zip":43110},{"code":430705,"districtCode":4307,"name":"หนองปลาปาก","zip":43130},{"code":431503,"districtCode":4315,"name":"หนองหลวง","zip":43120},{"code":430107,"districtCode":4301,"name":"หาดคำ","zip":43000},{"code":430108,"districtCode":4301,"name":"หินโงม","zip":43000},{"code":430507,"districtCode":4305,"name":"เหล่าต่างคำ","zip":43120},{"code":431505,"districtCode":4315,"name":"อุดมพร","zip":43120}]